README.rst
setup.cfg
setup.py
datawelder/__init__.py
datawelder/cat.py
datawelder/join.py
datawelder/partition.py
datawelder/printpart.py
datawelder/readwrite.py
datawelder/s3.py
datawelder/version.py
datawelder.egg-info/PKG-INFO
datawelder.egg-info/SOURCES.txt
datawelder.egg-info/dependency_links.txt
datawelder.egg-info/requires.txt
datawelder.egg-info/top_level.txt