Metadata-Version: 2.1
Name: datawelder
Version: 0.2.4
Summary: Joins large dataframes together
Home-page: https://github.com/ProfoundNetworks/datawelder
Author: Michael Penkov
Author-email: m@penkov.dev
Maintainer: Michael Penkov
Maintainer-email: m@penkov.dev
License: MIT
Download-URL: http://pypi.python.org/pypi/datawelder
Keywords: datawelder join dataframes
Platform: any
Classifier: Development Status :: 3 - Alpha
Classifier: Environment :: Console
Classifier: Intended Audience :: Developers
Classifier: License :: OSI Approved :: MIT License
Classifier: Operating System :: OS Independent
Classifier: Programming Language :: Python :: 3.6
Classifier: Programming Language :: Python :: 3.7
Classifier: Programming Language :: Python :: 3.8
Classifier: Topic :: System :: Distributed Computing
Requires-Python: >=3.6.*
Provides-Extra: test
